pyCallisto.py
pyCallistoUtils.py
pycallisto-1.2.3.dist-info/METADATA
pycallisto-1.2.3.dist-info/WHEEL
pycallisto-1.2.3.dist-info/top_level.txt
pycallisto-1.2.3.dist-info/RECORD
