Metadata-Version: 2.4
Name: pyCallisto
Version: 1.2.3
Summary: Python library for processing Callisto solar radio spectrometer data
Author-email: Ravindra Pawase <ravi.pawase@gmail.com>, "K. Sasikumar Raja" <sasikumarraja@gmail.com>, Mrutyunjaya Muduli <mudulimrutyunjaya42@gmail.com>
License-Expression: MIT
Project-URL: Homepage, https://github.com/ravipawase/pyCallisto
Project-URL: Bug Tracker, https://github.com/ravipawase/pyCallisto/issues
Requires-Python: >=3.7
Requires-Dist: numpy
Requires-Dist: matplotlib
Requires-Dist: astropy
Requires-Dist: beautifulsoup4
Requires-Dist: scipy
Provides-Extra: goes
Requires-Dist: sunpy>=4.0.0; extra == "goes"
Requires-Dist: drms; extra == "goes"
Requires-Dist: zeep; extra == "goes"
Requires-Dist: lxml; extra == "goes"
Requires-Dist: h5netcdf; extra == "goes"
Requires-Dist: h5py; extra == "goes"
Requires-Dist: cdflib; extra == "goes"
Requires-Dist: reproject; extra == "goes"
Requires-Dist: mpl-animators; extra == "goes"
Provides-Extra: all
Requires-Dist: sunpy>=4.0.0; extra == "all"
Requires-Dist: drms; extra == "all"
Requires-Dist: zeep; extra == "all"
Requires-Dist: lxml; extra == "all"
Requires-Dist: h5netcdf; extra == "all"
Requires-Dist: h5py; extra == "all"
Requires-Dist: cdflib; extra == "all"
Requires-Dist: reproject; extra == "all"
Requires-Dist: mpl-animators; extra == "all"
